lazyplotly/__init__.py
lazyplotly-1.2.dist-info/METADATA
lazyplotly-1.2.dist-info/WHEEL
lazyplotly-1.2.dist-info/top_level.txt
lazyplotly-1.2.dist-info/RECORD
