Metadata-Version: 2.1
Name: lazyplotly
Version: 1.2
Summary: A wrapper of plolty which makes adding widget much more easy (and lazy)
Home-page: https://github.com/billju/lazyplotly
Author: chuboy
License: UNKNOWN
Platform: UNKNOWN
Classifier: Topic :: Scientific/Engineering :: Visualization
